{
  "Version": 0,
  "Name": "Minimap",
  "Description": "",
  "Image": "",
  "Priority": 2,
  "Type": "Single",
  "DefaultSettings": 0,
  "Options": [
    {
      "Name": "Zodiark Square (Dark)",
      "Description": "",
      "Files": {
        "ui/uld/navimap_hr1.tex": "minimap\\zodiark\\square\\ui\\uld\\navimap_hr1.tex",
        "ui/uld/navimap_mask_hr1.tex": "minimap\\zodiark\\square\\ui\\uld\\navimap_mask_hr1.tex"
      },
      "FileSwaps": {},
      "Manipulations": []
    },
    {
      "Name": "Zodiark Circle (Dark)",
      "Description": "",
      "Files": {
        "ui/uld/navimap_hr1.tex": "minimap\\zodiark\\circle\\ui\\uld\\navimap_hr1.tex",
        "ui/uld/navimap_mask_hr1.tex": "minimap\\zodiark\\circle\\ui\\uld\\navimap_mask_hr1.tex"
      },
      "FileSwaps": {},
      "Manipulations": []
    },
    {
      "Name": "Hydaelyn Square (Light)",
      "Description": "",
      "Files": {
        "ui/uld/navimap_hr1.tex": "minimap\\hydaelyn\\square\\ui\\uld\\navimap_hr1.tex",
        "ui/uld/navimap_mask_hr1.tex": "minimap\\hydaelyn\\square\\ui\\uld\\navimap_mask_hr1.tex"
      },
      "FileSwaps": {},
      "Manipulations": []
    },
    {
      "Name": "Hydaelyn Circle (Light)",
      "Description": "",
      "Files": {
        "ui/uld/navimap_hr1.tex": "minimap\\hydaelyn\\circle\\ui\\uld\\navimap_hr1.tex",
        "ui/uld/navimap_mask_hr1.tex": "minimap\\hydaelyn\\circle\\ui\\uld\\navimap_mask_hr1.tex"
      },
      "FileSwaps": {},
      "Manipulations": []
    }
  ]
}